izypack4class10.py
plus10.py
izypack4class10-1.0.dist-info/LICENCE.txt
izypack4class10-1.0.dist-info/METADATA
izypack4class10-1.0.dist-info/WHEEL
izypack4class10-1.0.dist-info/top_level.txt
izypack4class10-1.0.dist-info/RECORD
