Metadata-Version: 2.1
Name: izypack4class10
Version: 1.0
Summary: Why not to add 10?
Home-page: http://meteo.lt
Author: Who cares?
Author-email: name.surname@gmail.com
License: MIT
License-File: LICENCE.txt
